pulumi_akamai/__init__.py
pulumi_akamai/_inputs.py
pulumi_akamai/_utilities.py
pulumi_akamai/apidefinitions_activation.py
pulumi_akamai/apidefinitions_api.py
pulumi_akamai/apidefinitions_resource_operations.py
pulumi_akamai/app_sec_activations.py
pulumi_akamai/app_sec_advanced_settings_evasive_path_match.py
pulumi_akamai/app_sec_advanced_settings_logging.py
pulumi_akamai/app_sec_advanced_settings_pragma_header.py
pulumi_akamai/app_sec_advanced_settings_prefetch.py
pulumi_akamai/app_sec_api_constraints_protection.py
pulumi_akamai/app_sec_api_request_constraints.py
pulumi_akamai/app_sec_attack_group.py
pulumi_akamai/app_sec_by_pass_network_list.py
pulumi_akamai/app_sec_configuration.py
pulumi_akamai/app_sec_configuration_rename.py
pulumi_akamai/app_sec_custom_deny.py
pulumi_akamai/app_sec_custom_rule.py
pulumi_akamai/app_sec_custom_rule_action.py
pulumi_akamai/app_sec_eval.py
pulumi_akamai/app_sec_eval_group.py
pulumi_akamai/app_sec_eval_penalty_box.py
pulumi_akamai/app_sec_eval_rule.py
pulumi_akamai/app_sec_ip_geo.py
pulumi_akamai/app_sec_ip_geo_protection.py
pulumi_akamai/app_sec_malware_policy.py
pulumi_akamai/app_sec_malware_policy_action.py
pulumi_akamai/app_sec_malware_policy_actions.py
pulumi_akamai/app_sec_malware_protection.py
pulumi_akamai/app_sec_match_target.py
pulumi_akamai/app_sec_match_target_sequence.py
pulumi_akamai/app_sec_penalty_box.py
pulumi_akamai/app_sec_rate_policy.py
pulumi_akamai/app_sec_rate_policy_action.py
pulumi_akamai/app_sec_rate_protection.py
pulumi_akamai/app_sec_reputation_profile.py
pulumi_akamai/app_sec_reputation_profile_action.py
pulumi_akamai/app_sec_reputation_profile_analysis.py
pulumi_akamai/app_sec_reputation_protection.py
pulumi_akamai/app_sec_rule.py
pulumi_akamai/app_sec_rule_upgrade.py
pulumi_akamai/app_sec_security_policy.py
pulumi_akamai/app_sec_security_policy_rename.py
pulumi_akamai/app_sec_siem_settings.py
pulumi_akamai/app_sec_slow_post.py
pulumi_akamai/app_sec_slow_post_protection.py
pulumi_akamai-10.2.0.dist-info/METADATA
pulumi_akamai-10.2.0.dist-info/WHEEL
pulumi_akamai-10.2.0.dist-info/top_level.txt
pulumi_akamai-10.2.0.dist-info/RECORD
